cafe/__init__.py
cafe/core.py
cafe/example.py
cafeteria_simulation-1.0.2.dist-info/LICENSE
cafeteria_simulation-1.0.2.dist-info/METADATA
cafeteria_simulation-1.0.2.dist-info/WHEEL
cafeteria_simulation-1.0.2.dist-info/top_level.txt
cafeteria_simulation-1.0.2.dist-info/RECORD
