Metadata-Version: 2.1
Name: cafeteria-simulation
Version: 1.0.2
Summary: Python package for cafe simulation
Home-page: https://github.com/m-star18/cafeteria-simulation
Author: Ryusei Ito
Author-email: 31807@toyota.kosen-ac.jp
License: Apache Software License 2.0
Platform: UNKNOWN
Requires-Python: >=3.6, <3.9
Requires-Dist: setuptools (~=50.3.0)
Requires-Dist: matplotlib (~=3.3.2)
